bioe/__init__.py
bioe/bio.py
bio_e-0.0.1.dist-info/LICENSE
bio_e-0.0.1.dist-info/METADATA
bio_e-0.0.1.dist-info/WHEEL
bio_e-0.0.1.dist-info/top_level.txt
bio_e-0.0.1.dist-info/RECORD
