Metadata-Version: 2.1
Name: bio-e
Version: 0.0.1
Summary: A Python package for biology students.
Author-email: Atlas <thesupremerat0@gmail.com>
Project-URL: Homepage, https://github.com/pypa/sampleproject
Project-URL: Issues, https://github.com/pypa/sampleproject/issues
Classifier: Programming Language :: Python :: 3
Classifier: License :: OSI Approved :: MIT License
Classifier: Operating System :: OS Independent
Requires-Python: >=3.8
License-File: LICENSE
